[1,["518/nhpftIQakgo3C8ZtqM@f9941","23qhoLnaZBXK0iEVn8gUPO@6c48a","39OKnsHRdNDbXQlPIvs+hB@6c48a","393hn6lbJMyroY8WYpHQLY@6c48a","518/nhpftIQakgo3C8ZtqM@6c48a","059qOoYTtMDLQOtpuH61Of@f9941","d5m+OFEhdGKq1jvM1WeNBK@f9941","23qhoLnaZBXK0iEVn8gUPO@f9941","393hn6lbJMyroY8WYpHQLY@f9941","75qEATgx1CyZPzxW5rsNLD@f9941","39OKnsHRdNDbXQlPIvs+hB@f9941","7cSD/B/fZKuY5rI09wzMgk@f9941","75qEATgx1CyZPzxW5rsNLD@6c48a","7cSD/B/fZKuY5rI09wzMgk@6c48a","d5m+OFEhdGKq1jvM1WeNBK@6c48a"],["node","_spriteFrame","_textureSource","root","data","_parent"],[["cc.Node",["_name","_layer","_active","_components","_prefab","_parent","_children","_lpos"],0,9,4,1,2,5],"cc.SpriteFrame",["cc.Sprite",["_sizeMode","node","__prefab","_spriteFrame","_color"],2,1,4,6,5],["cc.Prefab",["_name"],2],["cc.UITransform",["node","__prefab","_contentSize"],3,1,4,5],["cc.CompPrefabInfo",["fileId"],2],["c1e6eNzqd5PlZ3tGZ0qJG8F",["node","__prefab"],3,1,4],["cc.PrefabInfo",["fileId","instance","targetOverrides","nestedPrefabInstanceRoots","root","asset"],-1,1,1],["cc.UIOpacity",["_opacity","node","__prefab"],2,1,4]],[[5,0,2],[4,0,1,2,1],[7,0,1,2,3,4,5,5],[2,0,1,2,3,2],[0,0,1,5,3,4,7,3],[0,0,1,5,6,3,4,7,3],[3,0,2],[0,0,1,6,3,4,3],[0,0,1,5,6,3,4,3],[0,0,1,3,4,7,3],[0,0,1,5,3,4,3],[0,0,2,1,5,6,3,4,7,4],[0,0,2,1,5,3,4,4],[6,0,1,1],[2,0,1,2,4,3,2],[8,0,1,2,2]],[[[{"name":"2","rect":{"x":4,"y":5,"width":151,"height":69},"offset":{"x":0.5,"y":-1.5},"originalSize":{"width":158,"height":76},"rotated":false,"capInsets":[0,0,0,0],"vertices":{"rawPosition":[-75.5,-34.5,0,75.5,-34.5,0,-75.5,34.5,0,75.5,34.5,0],"indexes":[0,1,2,2,1,3],"uv":[4,71,155,71,4,2,155,2],"nuv":[0.02531645569620253,0.02631578947368421,0.9810126582278481,0.02631578947368421,0.02531645569620253,0.9342105263157895,0.9810126582278481,0.9342105263157895],"minPos":{"x":-75.5,"y":-34.5,"z":0},"maxPos":{"x":75.5,"y":34.5,"z":0}},"packable":true,"pixelsToUnit":100,"pivot":{"x":0.5,"y":0.5},"meshType":0}],[1],0,[0],[2],[1]],[[{"name":"qq","rect":{"x":4,"y":7,"width":288,"height":306},"offset":{"x":-1.5,"y":5},"originalSize":{"width":299,"height":330},"rotated":false,"capInsets":[0,0,0,0],"vertices":{"rawPosition":[-144,-153,0,144,-153,0,-144,153,0,144,153,0],"indexes":[0,1,2,2,1,3],"uv":[4,323,292,323,4,17,292,17],"nuv":[0.013377926421404682,0.051515151515151514,0.9765886287625418,0.051515151515151514,0.013377926421404682,0.9787878787878788,0.9765886287625418,0.9787878787878788],"minPos":{"x":-144,"y":-153,"z":0},"maxPos":{"x":144,"y":153,"z":0}},"packable":true,"pixelsToUnit":100,"pivot":{"x":0.5,"y":0.5},"meshType":0}],[1],0,[0],[2],[2]],[[{"name":"3","rect":{"x":2,"y":6,"width":115,"height":208},"offset":{"x":-2.5,"y":-2},"originalSize":{"width":124,"height":216},"rotated":false,"capInsets":[0,0,0,0],"vertices":{"rawPosition":[-57.5,-104,0,57.5,-104,0,-57.5,104,0,57.5,104,0],"indexes":[0,1,2,2,1,3],"uv":[2,210,117,210,2,2,117,2],"nuv":[0.016129032258064516,0.009259259259259259,0.9435483870967742,0.009259259259259259,0.016129032258064516,0.9722222222222222,0.9435483870967742,0.9722222222222222],"minPos":{"x":-57.5,"y":-104,"z":0},"maxPos":{"x":57.5,"y":104,"z":0}},"packable":true,"pixelsToUnit":100,"pivot":{"x":0.5,"y":0.5},"meshType":0}],[1],0,[0],[2],[3]],[[{"name":"1","rect":{"x":7,"y":4,"width":28,"height":106},"offset":{"x":0.5,"y":-1},"originalSize":{"width":41,"height":112},"rotated":false,"capInsets":[0,0,0,0],"vertices":{"rawPosition":[-14,-53,0,14,-53,0,-14,53,0,14,53,0],"indexes":[0,1,2,2,1,3],"uv":[7,108,35,108,7,2,35,2],"nuv":[0.17073170731707318,0.017857142857142856,0.8536585365853658,0.017857142857142856,0.17073170731707318,0.9642857142857143,0.8536585365853658,0.9642857142857143],"minPos":{"x":-14,"y":-53,"z":0},"maxPos":{"x":14,"y":53,"z":0}},"packable":true,"pixelsToUnit":100,"pivot":{"x":0.5,"y":0.5},"meshType":0}],[1],0,[0],[2],[4]],[[[6,"Character"],[7,"Character",33554432,[-4,-5,-6,-7],[[1,-2,[0,"d6cQq7awZLMZHPG3Gr7Cdf"],[5,486,486]],[13,-3,[0,"1f6t3rpgVHP7uNZKBFO/w+"]]],[2,"81UhQs9SVPk68x4c/DOVhJ",null,null,null,-1,0]],[8,"Hanzi",33554432,1,[-10,-11,-12,-13,-14],[[1,-8,[0,"023tTgJNtJh5n1Lzoge/Lw"],[5,299,330]],[3,2,-9,[0,"52IiEzoFZFf6G1OdIycI/V"],6]],[2,"abOIDIV+pDXYsQw6D/p9dF",null,null,null,1,0]],[9,"Sprite",33554432,[[1,-15,[0,"77TbSgXmlJJ6AfETHfbySi"],[5,41,144]],[14,0,-16,[0,"daoI5XmalGB6l1dXKVJSr2"],[4,4279045628],7],[15,120,-17,[0,"52JzXaDIBIhLgrlbvxHYlP"]]],[2,"4fQf5Z2mhClqfP4t4DPIO2",null,null,null,1,0],[1,0,16,0]],[10,"CharBg",33554432,1,[[1,-18,[0,"17o1hgBpZK8rLZHUPF0PWW"],[5,448,448]],[3,0,-19,[0,"91/NIGy71Cs4Xkd8Uo0NVN"],0]],[2,"75AZjcXqRIMojS785SWaoX",null,null,null,1,0]],[4,"0",33554432,2,[[1,-20,[0,"56hudEf/RJhaoJKesqsNhn"],[5,132,52]],[3,2,-21,[0,"15Q4f07slLQpg1a7E4dHfU"],1]],[2,"12x1Ke4uZAgJqbBIhTV9ua",null,null,null,1,0],[1,-67,139,0]],[4,"1",33554432,2,[[1,-22,[0,"76gF31NdFFKIbO652/gDEU"],[5,41,112]],[3,2,-23,[0,"b6ykDWdiJCIqCnPWstDr1k"],2]],[2,"aenimpRk5MRa5JizHNUKqk",null,null,null,1,0],[1,-67,70,0]],[4,"2",33554432,2,[[1,-24,[0,"35l5he3yxI6pkWOnerjXdf"],[5,158,76]],[3,2,-25,[0,"45BFgo1fRKS6qgpjgCX2kR"],3]],[2,"43w/HDLCNHUatMDRORGVxM",null,null,null,1,0],[1,-82,10,0]],[4,"3",33554432,2,[[1,-26,[0,"b0CjQ8FrRH5a9WGG9nzqiU"],[5,124,216]],[3,2,-27,[0,"9cMgugSR1AEoI5IUyQGawJ"],4]],[2,"f4M7eXfqhFmqWVbdngBa4i",null,null,null,1,0],[1,91,57,0]],[4,"4",33554432,2,[[1,-28,[0,"1cGcMM5VFDUo/i8Ftqcke3"],[5,59,299]],[3,2,-29,[0,"e3hEdYQmFJzZQZPYF5x26/"],5]],[2,"07P7zo5YdDzKLNkkE871aZ",null,null,null,1,0],[1,29,-9,0]],[5,"Points",33554432,1,[-31],[[1,-30,[0,"17L2jVtDhInLbVfr67m6wQ"],[5,448,460]]],[2,"46wj7xoaZBRoW6ro6bBR/I",null,null,null,1,0],[1,0,-3.458,0]],[11,"1_0",false,33554432,10,[3],[[1,-32,[0,"b1y3/z6cxOT6bBXL/j9JaG"],[5,89.06200000000001,221]]],[2,"23RRy0SMxOIadQtlNH1hGv",null,null,null,1,0],[1,-66.62700000000001,-23.814000000000078,0]],[5,"NewHanzi",33554432,1,[-34],[[1,-33,[0,"6bvxcYFkdKJpR+4lqT2qpw"],[5,280,230]]],[2,"faLn+yCXxD0KBNQAoc90r/",null,null,null,1,0],[1,0,-3.415,0]],[12,"1_0",false,33554432,12,[[1,-35,[0,"efPf3b4LJPrKAeyGLqOgM0"],[5,335,341]],[3,2,-36,[0,"bae+iJbKBGTaacm6WrrLTK"],8]],[2,"1eTeLiD4FMybK0xQDcCBN3",null,null,null,1,0]]],0,[0,3,1,0,0,1,0,0,1,0,-1,4,0,-2,2,0,-3,10,0,-4,12,0,0,2,0,0,2,0,-1,5,0,-2,6,0,-3,7,0,-4,8,0,-5,9,0,0,3,0,0,3,0,0,3,0,0,4,0,0,4,0,0,5,0,0,5,0,0,6,0,0,6,0,0,7,0,0,7,0,0,8,0,0,8,0,0,9,0,0,9,0,0,10,0,-1,11,0,0,11,0,0,12,0,-1,13,0,0,13,0,0,13,0,4,1,3,5,11,36],[0,0,0,0,0,0,0,0,0],[1,1,1,1,1,1,1,1,1],[5,6,0,7,8,9,10,0,11]],[[{"name":"4","rect":{"x":6,"y":6,"width":38,"height":292},"offset":{"x":-4.5,"y":-2.5},"originalSize":{"width":59,"height":299},"rotated":false,"capInsets":[0,0,0,0],"vertices":{"rawPosition":[-19,-146,0,19,-146,0,-19,146,0,19,146,0],"indexes":[0,1,2,2,1,3],"uv":[6,293,44,293,6,1,44,1],"nuv":[0.1016949152542373,0.0033444816053511705,0.7457627118644068,0.0033444816053511705,0.1016949152542373,0.979933110367893,0.7457627118644068,0.979933110367893],"minPos":{"x":-19,"y":-146,"z":0},"maxPos":{"x":19,"y":146,"z":0}},"packable":true,"pixelsToUnit":100,"pivot":{"x":0.5,"y":0.5},"meshType":0}],[1],0,[0],[2],[12]],[[{"name":"30","rect":{"x":4,"y":14,"width":313,"height":318},"offset":{"x":-7,"y":-2.5},"originalSize":{"width":335,"height":341},"rotated":false,"capInsets":[0,0,0,0],"vertices":{"rawPosition":[-156.5,-159,0,156.5,-159,0,-156.5,159,0,156.5,159,0],"indexes":[0,1,2,2,1,3],"uv":[4,327,317,327,4,9,317,9],"nuv":[0.011940298507462687,0.026392961876832845,0.9462686567164179,0.026392961876832845,0.011940298507462687,0.9589442815249267,0.9462686567164179,0.9589442815249267],"minPos":{"x":-156.5,"y":-159,"z":0},"maxPos":{"x":156.5,"y":159,"z":0}},"packable":true,"pixelsToUnit":100,"pivot":{"x":0.5,"y":0.5},"meshType":0}],[1],0,[0],[2],[13]],[[{"name":"0","rect":{"x":10,"y":12,"width":122,"height":38},"offset":{"x":5,"y":-5},"originalSize":{"width":132,"height":52},"rotated":false,"capInsets":[0,0,0,0],"vertices":{"rawPosition":[-61,-19,0,61,-19,0,-61,19,0,61,19,0],"indexes":[0,1,2,2,1,3],"uv":[10,40,132,40,10,2,132,2],"nuv":[0.07575757575757576,0.038461538461538464,1,0.038461538461538464,0.07575757575757576,0.7692307692307693,1,0.7692307692307693],"minPos":{"x":-61,"y":-19,"z":0},"maxPos":{"x":61,"y":19,"z":0}},"packable":true,"pixelsToUnit":100,"pivot":{"x":0.5,"y":0.5},"meshType":0}],[1],0,[0],[2],[14]]]]
